splitspy/__init__.py
splitspy/outline.py
splitspy/graph/__init__.py
splitspy/graph/draw.py
splitspy/graph/graph.py
splitspy/nnet/__init__.py
splitspy/nnet/distances.py
splitspy/nnet/nnet_algo.py
splitspy/nnet/nnet_cycle.py
splitspy/nnet/nnet_node.py
splitspy/nnet/nnet_splits.py
splitspy/outlines/__init__.py
splitspy/outlines/event.py
splitspy/outlines/outline_algo.py
splitspy/splits/__init__.py
splitspy/splits/basic_split.py
splitspy/splits/splits_io.py
SplitsPy-0.0.10.dist-info/LICENSE
SplitsPy-0.0.10.dist-info/METADATA
SplitsPy-0.0.10.dist-info/WHEEL
SplitsPy-0.0.10.dist-info/entry_points.txt
SplitsPy-0.0.10.dist-info/top_level.txt
SplitsPy-0.0.10.dist-info/RECORD
