Metadata-Version: 2.1
Name: SplitsPy
Version: 0.0.10
Summary: Phylogenetic outlines
Home-page: http://github.com/husonlab/SplitsPhy
Author: Daniel H. Huson
Author-email: daniel.huson@uni-tuebingen.de
License: GPL
Keywords: phylogenetics,network
Platform: UNKNOWN
Requires-Python: >=3.5, <4
Requires-Dist: numpy
Requires-Dist: pillow
